{
  "/_app": "pages/_app.js",
  "/_error": "pages/_error.js",
  "/[formId]/responses": "pages/[formId]/responses.html",
  "/api/hello": "pages/api/hello.js",
  "/completepayment/[paymentProvider]/[orderId]": "pages/completepayment/[paymentProvider]/[orderId].html",
  "/confirmation/[id]": "pages/confirmation/[id].html",
  "/create": "pages/create.html",
  "/form/demo": "pages/form/demo.html",
  "/form/dynamic": "pages/form/dynamic.html",
  "/form/paymentStatus": "pages/form/paymentStatus.html",
  "/form/pedes2022": "pages/form/pedes2022.html",
  "/form/test": "pages/form/test.html",
  "/": "pages/index.html",
  "/form/emergence": "pages/form/emergence.js",
  "/form/ypupskill": "pages/form/ypupskill.js",
  "/form/indicon2022special": "pages/form/indicon2022special.js",
  "/_document": "pages/_document.js",
  "/form/indicon2022": "pages/form/indicon2022.js",
  "/404": "pages/404.html"
}